{
    "version": "1.1.0",
    "versionCode": 10,
    "updateUrl": "https://github.com/mistycrown/lumostime2/releases/latest",
    "releaseNotes": "v1.1.0\n• 增加修改日课模板时对历史数据的检测\n• 禁用手机端放大缩小页面\n• 增加日程图双指缩放功能\n• 增加点击日历跳转到当天记录的功能\n• 增加分享记录为卡片的功能\n• 增加自动日课的功能，通过条件判断自动判断完成、未完成\n• 增加自动生成review的偏好设置\n• 增加环形图导出分享卡片的功能\n• 增加引导页重新从模板导入的功能\n• 增加日课打卡数据同步到时间轴的功能\n• 增加标签/分类/领域/筛选器/待办详情中时间线历史右侧的快速切换悬浮条\n• 更新示例待办数据\n• 修复待办详情时间线内进度不显示的问题\n• 增加memoir页面通过左右滑动切换上月下月的功能\n• 增加自定义条目折叠字数的功能\n• 增加AI生成引言的功能",
    "forceUpdate": false
}